COPYING
MANIFEST.in
README.rst
phablet.py
setup.cfg
setup.py
phablet.egg-info/PKG-INFO
phablet.egg-info/SOURCES.txt
phablet.egg-info/dependency_links.txt
phablet.egg-info/entry_points.txt
phablet.egg-info/top_level.txt
phablet.egg-info/zip-safe