Metadata-Version: 1.0
Name: phablet
Version: 0.1
Summary: Python 2/3 API for Ubuntu Phablet
Home-page: https://github.com/zyga/python-phablet
Author: Zygmunt Krynicki
Author-email: zygmunt.krynicki@canonical.com
License: GPLv3
Platform: UNKNOWN
